{"action":"labeled","number":37,"pull_request":{"url":"https://github.wdf.sap.corp/api/v3/repos/I516376/test-pr/pulls/37","id":2261706,"node_id":"MDExOlB1bGxSZXF1ZXN0MjI2MTcwNg==","html_url":"https://github.wdf.sap.corp/I516376/test-pr/pull/37","diff_url":"https://github.wdf.sap.corp/I516376/test-pr/pull/37.diff","patch_url":"https://github.wdf.sap.corp/I516376/test-pr/pull/37.patch","issue_url":"https://github.wdf.sap.corp/api/v3/repos/I516376/test-pr/issues/37","number":37,"state":"open","locked":false,"title":"Update README.md","user":{"login":"I516376","id":53960,"node_id":"MDQ6VXNlcjUzOTYw","avatar_url":"https://github.wdf.sap.corp/avatars/u/53960?","gravatar_id":"","url":"https://github.wdf.sap.corp/api/v3/users/I516376","html_url":"https://github.wdf.sap.corp/I516376","followers_url":"https://github.wdf.sap.corp/api/v3/users/I516376/followers","following_url":"https://github.wdf.sap.corp/api/v3/users/I516376/following{/other_user}","gists_url":"https://github.wdf.sap.corp/api/v3/users/I516376/gists{/gist_id}","starred_url":"https://github.wdf.sap.corp/api/v3/users/I516376/starred{/owner}{/repo}","subscriptions_url":"https://github.wdf.sap.corp/api/v3/users/I516376/subscriptions","organizations_url":"https://github.wdf.sap.corp/api/v3/users/I516376/orgs","repos_url":"https://github.wdf.sap.corp/api/v3/users/I516376/repos","events_url":"https://github.wdf.sap.corp/api/v3/users/I516376/events{/privacy}","received_events_url":"https://github.wdf.sap.corp/api/v3/users/I516376/received_events","type":"User","site_admin":false},"body":"## Please do note that filling this PR temaplate is mandatory for your PR to be merge in DSP-Release:\r\n\r\n### ML-Component name for PR:\r\nDSP-CORE-OPERATORS\r\n\r\n\r\n### Detailed Description of change this PR contains:\r\n\r\nHot fixes for DI:2003\r\n\r\n### Provide links or keys to any relevant tickets, JIRA or other resources:\r\n\r\nHANA ML Operators:\r\nhttps://sapjira.wdf.sap.corp/browse/DIBUGS-2937\r\nArtifact Producer/Consumer Operator:\r\nhttps://sapjira.wdf.sap.corp/browse/DIBUGS-3098\r\nAutoML:\r\nhttps://sapjira.wdf.sap.corp/browse/DIBUGS-2949\r\nhttps://sapjira.wdf.sap.corp/browse/DIBUGS-2691\r\n\r\n\r\n### PR is raised for what purpose to solve: \r\n\r\nPlease write your response from below:\r\n\r\n- [ ] feat (new feature)\r\n- [x] fix  (BugFix)\r\n- [ ] refactor (refactoring production code)\r\n- [ ] enhancements (new enhancements to existing feature)\r\n- [ ] style (formatting, missing semi colons, etc; no code change)\r\n- [ ] docs  (changes to documentation)\r\n- [ ] test  (Acceptance/Integration)\r\n- [ ] chore (updating grunt tasks etc; no production code change)\r\n- [ ] other (If not present in the above option , please fill the details)\r\n\r\n\r\n### Passed CI and Integration Test Result link:\r\nhttps://jenkins.ml.only.sap/blue/organizations/jenkins/DSP%2Fdsp-core-operators.environment/detail/PR-619/7/tests\r\n\r\n### Remember to:\r\n   * Capitalize the subject line with details of your component new version , example- DSP-NOTEBOOK[ReleasedVersion]- Release Name\r\n   * Use Draft pull request for work in progress\r\n   * Use relevant labels for your PR\r\n   * Please put I343977, I323878 and D063250 as reviwers along with other reviewers (if any)\r\n   \r\n\r\n\r\n","created_at":"2020-04-17T10:28:34Z","updated_at":"2020-04-17T10:28:34Z","closed_at":null,"merged_at":null,"merge_commit_sha":null,"assignee":null,"assignees":[],"requested_reviewers":[{"login":"marvin-sap-di-bot-assistant","id":61826,"node_id":"MDQ6VXNlcjYxODI2","avatar_url":"https://github.wdf.sap.corp/avatars/u/61826?","gravatar_id":"","url":"https://github.wdf.sap.corp/api/v3/users/marvin-sap-di-bot-assistant","html_url":"https://github.wdf.sap.corp/marvin-sap-di-bot-assistant","followers_url":"https://github.wdf.sap.corp/api/v3/users/marvin-sap-di-bot-assistant/followers","following_url":"https://github.wdf.sap.corp/api/v3/users/marvin-sap-di-bot-assistant/following{/other_user}","gists_url":"https://github.wdf.sap.corp/api/v3/users/marvin-sap-di-bot-assistant/gists{/gist_id}","starred_url":"https://github.wdf.sap.corp/api/v3/users/marvin-sap-di-bot-assistant/starred{/owner}{/repo}","subscriptions_url":"https://github.wdf.sap.corp/api/v3/users/marvin-sap-di-bot-assistant/subscriptions","organizations_url":"https://github.wdf.sap.corp/api/v3/users/marvin-sap-di-bot-assistant/orgs","repos_url":"https://github.wdf.sap.corp/api/v3/users/marvin-sap-di-bot-assistant/repos","events_url":"https://github.wdf.sap.corp/api/v3/users/marvin-sap-di-bot-assistant/events{/privacy}","received_events_url":"https://github.wdf.sap.corp/api/v3/users/marvin-sap-di-bot-assistant/received_events","type":"User","site_admin":false}],"requested_teams":[],"labels":[{"id":2799646,"node_id":"MDU6TGFiZWwyNzk5NjQ2","url":"https://github.wdf.sap.corp/api/v3/repos/I516376/test-pr/labels/release20","name":"release20","color":"db7262","default":false,"description":""}],"milestone":null,"commits_url":"https://github.wdf.sap.corp/api/v3/repos/I516376/test-pr/pulls/37/commits","review_comments_url":"https://github.wdf.sap.corp/api/v3/repos/I516376/test-pr/pulls/37/comments","review_comment_url":"https://github.wdf.sap.corp/api/v3/repos/I516376/test-pr/pulls/comments{/number}","comments_url":"https://github.wdf.sap.corp/api/v3/repos/I516376/test-pr/issues/37/comments","statuses_url":"https://github.wdf.sap.corp/api/v3/repos/I516376/test-pr/statuses/5248091189404d7a94789600a8b7c26791913c52","head":{"label":"I516376:test","ref":"test","sha":"5248091189404d7a94789600a8b7c26791913c52","user":{"login":"I516376","id":53960,"node_id":"MDQ6VXNlcjUzOTYw","avatar_url":"https://github.wdf.sap.corp/avatars/u/53960?","gravatar_id":"","url":"https://github.wdf.sap.corp/api/v3/users/I516376","html_url":"https://github.wdf.sap.corp/I516376","followers_url":"https://github.wdf.sap.corp/api/v3/users/I516376/followers","following_url":"https://github.wdf.sap.corp/api/v3/users/I516376/following{/other_user}","gists_url":"https://github.wdf.sap.corp/api/v3/users/I516376/gists{/gist_id}","starred_url":"https://github.wdf.sap.corp/api/v3/users/I516376/starred{/owner}{/repo}","subscriptions_url":"https://github.wdf.sap.corp/api/v3/users/I516376/subscriptions","organizations_url":"https://github.wdf.sap.corp/api/v3/users/I516376/orgs","repos_url":"https://github.wdf.sap.corp/api/v3/users/I516376/repos","events_url":"https://github.wdf.sap.corp/api/v3/users/I516376/events{/privacy}","received_events_url":"https://github.wdf.sap.corp/api/v3/users/I516376/received_events","type":"User","site_admin":false},"repo":{"id":355247,"node_id":"MDEwOlJlcG9zaXRvcnkzNTUyNDc=","name":"test-pr","full_name":"I516376/test-pr","private":false,"owner":{"login":"I516376","id":53960,"node_id":"MDQ6VXNlcjUzOTYw","avatar_url":"https://github.wdf.sap.corp/avatars/u/53960?","gravatar_id":"","url":"https://github.wdf.sap.corp/api/v3/users/I516376","html_url":"https://github.wdf.sap.corp/I516376","followers_url":"https://github.wdf.sap.corp/api/v3/users/I516376/followers","following_url":"https://github.wdf.sap.corp/api/v3/users/I516376/following{/other_user}","gists_url":"https://github.wdf.sap.corp/api/v3/users/I516376/gists{/gist_id}","starred_url":"https://github.wdf.sap.corp/api/v3/users/I516376/starred{/owner}{/repo}","subscriptions_url":"https://github.wdf.sap.corp/api/v3/users/I516376/subscriptions","organizations_url":"https://github.wdf.sap.corp/api/v3/users/I516376/orgs","repos_url":"https://github.wdf.sap.corp/api/v3/users/I516376/repos","events_url":"https://github.wdf.sap.corp/api/v3/users/I516376/events{/privacy}","received_events_url":"https://github.wdf.sap.corp/api/v3/users/I516376/received_events","type":"User","site_admin":false},"html_url":"https://github.wdf.sap.corp/I516376/test-pr","description":null,"fork":false,"url":"https://github.wdf.sap.corp/api/v3/repos/I516376/test-pr","forks_url":"https://github.wdf.sap.corp/api/v3/repos/I516376/test-pr/forks","keys_url":"https://github.wdf.sap.corp/api/v3/repos/I516376/test-pr/keys{/key_id}","collaborators_url":"https://github.wdf.sap.corp/api/v3/repos/I516376/test-pr/collaborators{/collaborator}","teams_url":"https://github.wdf.sap.corp/api/v3/repos/I516376/test-pr/teams","hooks_url":"https://github.wdf.sap.corp/api/v3/repos/I516376/test-pr/hooks","issue_events_url":"https://github.wdf.sap.corp/api/v3/repos/I516376/test-pr/issues/events{/number}","events_url":"https://github.wdf.sap.corp/api/v3/repos/I516376/test-pr/events","assignees_url":"https://github.wdf.sap.corp/api/v3/repos/I516376/test-pr/assignees{/user}","branches_url":"https://github.wdf.sap.corp/api/v3/repos/I516376/test-pr/branches{/branch}","tags_url":"https://github.wdf.sap.corp/api/v3/repos/I516376/test-pr/tags","blobs_url":"https://github.wdf.sap.corp/api/v3/repos/I516376/test-pr/git/blobs{/sha}","git_tags_url":"https://github.wdf.sap.corp/api/v3/repos/I516376/test-pr/git/tags{/sha}","git_refs_url":"https://github.wdf.sap.corp/api/v3/repos/I516376/test-pr/git/refs{/sha}","trees_url":"https://github.wdf.sap.corp/api/v3/repos/I516376/test-pr/git/trees{/sha}","statuses_url":"https://github.wdf.sap.corp/api/v3/repos/I516376/test-pr/statuses/{sha}","languages_url":"https://github.wdf.sap.corp/api/v3/repos/I516376/test-pr/languages","stargazers_url":"https://github.wdf.sap.corp/api/v3/repos/I516376/test-pr/stargazers","contributors_url":"https://github.wdf.sap.corp/api/v3/repos/I516376/test-pr/contributors","subscribers_url":"https://github.wdf.sap.corp/api/v3/repos/I516376/test-pr/subscribers","subscription_url":"https://github.wdf.sap.corp/api/v3/repos/I516376/test-pr/subscription","commits_url":"https://github.wdf.sap.corp/api/v3/repos/I516376/test-pr/commits{/sha}","git_commits_url":"https://github.wdf.sap.corp/api/v3/repos/I516376/test-pr/git/commits{/sha}","comments_url":"https://github.wdf.sap.corp/api/v3/repos/I516376/test-pr/comments{/number}","issue_comment_url":"https://github.wdf.sap.corp/api/v3/repos/I516376/test-pr/issues/comments{/number}","contents_url":"https://github.wdf.sap.corp/api/v3/repos/I516376/test-pr/contents/{+path}","compare_url":"https://github.wdf.sap.corp/api/v3/repos/I516376/test-pr/compare/{base}...{head}","merges_url":"https://github.wdf.sap.corp/api/v3/repos/I516376/test-pr/merges","archive_url":"https://github.wdf.sap.corp/api/v3/repos/I516376/test-pr/{archive_format}{/ref}","downloads_url":"https://github.wdf.sap.corp/api/v3/repos/I516376/test-pr/downloads","issues_url":"https://github.wdf.sap.corp/api/v3/repos/I516376/test-pr/issues{/number}","pulls_url":"https://github.wdf.sap.corp/api/v3/repos/I516376/test-pr/pulls{/number}","milestones_url":"https://github.wdf.sap.corp/api/v3/repos/I516376/test-pr/milestones{/number}","notifications_url":"https://github.wdf.sap.corp/api/v3/repos/I516376/test-pr/notifications{?since,all,participating}","labels_url":"https://github.wdf.sap.corp/api/v3/repos/I516376/test-pr/labels{/name}","releases_url":"https://github.wdf.sap.corp/api/v3/repos/I516376/test-pr/releases{/id}","deployments_url":"https://github.wdf.sap.corp/api/v3/repos/I516376/test-pr/deployments","created_at":"2020-04-07T15:33:20Z","updated_at":"2020-04-07T15:36:30Z","pushed_at":"2020-04-17T10:28:34Z","git_url":"git://github.wdf.sap.corp/I516376/test-pr.git","ssh_url":"git@github.wdf.sap.corp:I516376/test-pr.git","clone_url":"https://github.wdf.sap.corp/I516376/test-pr.git","svn_url":"https://github.wdf.sap.corp/I516376/test-pr","homepage":null,"size":2,"stargazers_count":0,"watchers_count":0,"language":null,"has_issues":true,"has_projects":true,"has_downloads":true,"has_wiki":true,"has_pages":false,"forks_count":0,"mirror_url":null,"archived":false,"disabled":false,"open_issues_count":1,"license":null,"forks":0,"open_issues":1,"watchers":0,"default_branch":"master"}},"base":{"label":"I516376:master","ref":"master","sha":"176eeb3a92897c69ec42e1c5df1ba7325fcf4d10","user":{"login":"I516376","id":53960,"node_id":"MDQ6VXNlcjUzOTYw","avatar_url":"https://github.wdf.sap.corp/avatars/u/53960?","gravatar_id":"","url":"https://github.wdf.sap.corp/api/v3/users/I516376","html_url":"https://github.wdf.sap.corp/I516376","followers_url":"https://github.wdf.sap.corp/api/v3/users/I516376/followers","following_url":"https://github.wdf.sap.corp/api/v3/users/I516376/following{/other_user}","gists_url":"https://github.wdf.sap.corp/api/v3/users/I516376/gists{/gist_id}","starred_url":"https://github.wdf.sap.corp/api/v3/users/I516376/starred{/owner}{/repo}","subscriptions_url":"https://github.wdf.sap.corp/api/v3/users/I516376/subscriptions","organizations_url":"https://github.wdf.sap.corp/api/v3/users/I516376/orgs","repos_url":"https://github.wdf.sap.corp/api/v3/users/I516376/repos","events_url":"https://github.wdf.sap.corp/api/v3/users/I516376/events{/privacy}","received_events_url":"https://github.wdf.sap.corp/api/v3/users/I516376/received_events","type":"User","site_admin":false},"repo":{"id":355247,"node_id":"MDEwOlJlcG9zaXRvcnkzNTUyNDc=","name":"test-pr","full_name":"I516376/test-pr","private":false,"owner":{"login":"I516376","id":53960,"node_id":"MDQ6VXNlcjUzOTYw","avatar_url":"https://github.wdf.sap.corp/avatars/u/53960?","gravatar_id":"","url":"https://github.wdf.sap.corp/api/v3/users/I516376","html_url":"https://github.wdf.sap.corp/I516376","followers_url":"https://github.wdf.sap.corp/api/v3/users/I516376/followers","following_url":"https://github.wdf.sap.corp/api/v3/users/I516376/following{/other_user}","gists_url":"https://github.wdf.sap.corp/api/v3/users/I516376/gists{/gist_id}","starred_url":"https://github.wdf.sap.corp/api/v3/users/I516376/starred{/owner}{/repo}","subscriptions_url":"https://github.wdf.sap.corp/api/v3/users/I516376/subscriptions","organizations_url":"https://github.wdf.sap.corp/api/v3/users/I516376/orgs","repos_url":"https://github.wdf.sap.corp/api/v3/users/I516376/repos","events_url":"https://github.wdf.sap.corp/api/v3/users/I516376/events{/privacy}","received_events_url":"https://github.wdf.sap.corp/api/v3/users/I516376/received_events","type":"User","site_admin":false},"html_url":"https://github.wdf.sap.corp/I516376/test-pr","description":null,"fork":false,"url":"https://github.wdf.sap.corp/api/v3/repos/I516376/test-pr","forks_url":"https://github.wdf.sap.corp/api/v3/repos/I516376/test-pr/forks","keys_url":"https://github.wdf.sap.corp/api/v3/repos/I516376/test-pr/keys{/key_id}","collaborators_url":"https://github.wdf.sap.corp/api/v3/repos/I516376/test-pr/collaborators{/collaborator}","teams_url":"https://github.wdf.sap.corp/api/v3/repos/I516376/test-pr/teams","hooks_url":"https://github.wdf.sap.corp/api/v3/repos/I516376/test-pr/hooks","issue_events_url":"https://github.wdf.sap.corp/api/v3/repos/I516376/test-pr/issues/events{/number}","events_url":"https://github.wdf.sap.corp/api/v3/repos/I516376/test-pr/events","assignees_url":"https://github.wdf.sap.corp/api/v3/repos/I516376/test-pr/assignees{/user}","branches_url":"https://github.wdf.sap.corp/api/v3/repos/I516376/test-pr/branches{/branch}","tags_url":"https://github.wdf.sap.corp/api/v3/repos/I516376/test-pr/tags","blobs_url":"https://github.wdf.sap.corp/api/v3/repos/I516376/test-pr/git/blobs{/sha}","git_tags_url":"https://github.wdf.sap.corp/api/v3/repos/I516376/test-pr/git/tags{/sha}","git_refs_url":"https://github.wdf.sap.corp/api/v3/repos/I516376/test-pr/git/refs{/sha}","trees_url":"https://github.wdf.sap.corp/api/v3/repos/I516376/test-pr/git/trees{/sha}","statuses_url":"https://github.wdf.sap.corp/api/v3/repos/I516376/test-pr/statuses/{sha}","languages_url":"https://github.wdf.sap.corp/api/v3/repos/I516376/test-pr/languages","stargazers_url":"https://github.wdf.sap.corp/api/v3/repos/I516376/test-pr/stargazers","contributors_url":"https://github.wdf.sap.corp/api/v3/repos/I516376/test-pr/contributors","subscribers_url":"https://github.wdf.sap.corp/api/v3/repos/I516376/test-pr/subscribers","subscription_url":"https://github.wdf.sap.corp/api/v3/repos/I516376/test-pr/subscription","commits_url":"https://github.wdf.sap.corp/api/v3/repos/I516376/test-pr/commits{/sha}","git_commits_url":"https://github.wdf.sap.corp/api/v3/repos/I516376/test-pr/git/commits{/sha}","comments_url":"https://github.wdf.sap.corp/api/v3/repos/I516376/test-pr/comments{/number}","issue_comment_url":"https://github.wdf.sap.corp/api/v3/repos/I516376/test-pr/issues/comments{/number}","contents_url":"https://github.wdf.sap.corp/api/v3/repos/I516376/test-pr/contents/{+path}","compare_url":"https://github.wdf.sap.corp/api/v3/repos/I516376/test-pr/compare/{base}...{head}","merges_url":"https://github.wdf.sap.corp/api/v3/repos/I516376/test-pr/merges","archive_url":"https://github.wdf.sap.corp/api/v3/repos/I516376/test-pr/{archive_format}{/ref}","downloads_url":"https://github.wdf.sap.corp/api/v3/repos/I516376/test-pr/downloads","issues_url":"https://github.wdf.sap.corp/api/v3/repos/I516376/test-pr/issues{/number}","pulls_url":"https://github.wdf.sap.corp/api/v3/repos/I516376/test-pr/pulls{/number}","milestones_url":"https://github.wdf.sap.corp/api/v3/repos/I516376/test-pr/milestones{/number}","notifications_url":"https://github.wdf.sap.corp/api/v3/repos/I516376/test-pr/notifications{?since,all,participating}","labels_url":"https://github.wdf.sap.corp/api/v3/repos/I516376/test-pr/labels{/name}","releases_url":"https://github.wdf.sap.corp/api/v3/repos/I516376/test-pr/releases{/id}","deployments_url":"https://github.wdf.sap.corp/api/v3/repos/I516376/test-pr/deployments","created_at":"2020-04-07T15:33:20Z","updated_at":"2020-04-07T15:36:30Z","pushed_at":"2020-04-17T10:28:34Z","git_url":"git://github.wdf.sap.corp/I516376/test-pr.git","ssh_url":"git@github.wdf.sap.corp:I516376/test-pr.git","clone_url":"https://github.wdf.sap.corp/I516376/test-pr.git","svn_url":"https://github.wdf.sap.corp/I516376/test-pr","homepage":null,"size":2,"stargazers_count":0,"watchers_count":0,"language":null,"has_issues":true,"has_projects":true,"has_downloads":true,"has_wiki":true,"has_pages":false,"forks_count":0,"mirror_url":null,"archived":false,"disabled":false,"open_issues_count":1,"license":null,"forks":0,"open_issues":1,"watchers":0,"default_branch":"master"}},"_links":{"self":{"href":"https://github.wdf.sap.corp/api/v3/repos/I516376/test-pr/pulls/37"},"html":{"href":"https://github.wdf.sap.corp/I516376/test-pr/pull/37"},"issue":{"href":"https://github.wdf.sap.corp/api/v3/repos/I516376/test-pr/issues/37"},"comments":{"href":"https://github.wdf.sap.corp/api/v3/repos/I516376/test-pr/issues/37/comments"},"review_comments":{"href":"https://github.wdf.sap.corp/api/v3/repos/I516376/test-pr/pulls/37/comments"},"review_comment":{"href":"https://github.wdf.sap.corp/api/v3/repos/I516376/test-pr/pulls/comments{/number}"},"commits":{"href":"https://github.wdf.sap.corp/api/v3/repos/I516376/test-pr/pulls/37/commits"},"statuses":{"href":"https://github.wdf.sap.corp/api/v3/repos/I516376/test-pr/statuses/5248091189404d7a94789600a8b7c26791913c52"}},"author_association":"OWNER","draft":false,"merged":false,"mergeable":null,"rebaseable":null,"mergeable_state":"unknown","merged_by":null,"comments":0,"review_comments":0,"maintainer_can_modify":false,"commits":1,"additions":2,"deletions":1,"changed_files":1},"label":{"id":2799646,"node_id":"MDU6TGFiZWwyNzk5NjQ2","url":"https://github.wdf.sap.corp/api/v3/repos/I516376/test-pr/labels/release20","name":"release20","color":"db7262","default":false,"description":""},"repository":{"id":355247,"node_id":"MDEwOlJlcG9zaXRvcnkzNTUyNDc=","name":"test-pr","full_name":"I516376/test-pr","private":false,"owner":{"login":"I516376","id":53960,"node_id":"MDQ6VXNlcjUzOTYw","avatar_url":"https://github.wdf.sap.corp/avatars/u/53960?","gravatar_id":"","url":"https://github.wdf.sap.corp/api/v3/users/I516376","html_url":"https://github.wdf.sap.corp/I516376","followers_url":"https://github.wdf.sap.corp/api/v3/users/I516376/followers","following_url":"https://github.wdf.sap.corp/api/v3/users/I516376/following{/other_user}","gists_url":"https://github.wdf.sap.corp/api/v3/users/I516376/gists{/gist_id}","starred_url":"https://github.wdf.sap.corp/api/v3/users/I516376/starred{/owner}{/repo}","subscriptions_url":"https://github.wdf.sap.corp/api/v3/users/I516376/subscriptions","organizations_url":"https://github.wdf.sap.corp/api/v3/users/I516376/orgs","repos_url":"https://github.wdf.sap.corp/api/v3/users/I516376/repos","events_url":"https://github.wdf.sap.corp/api/v3/users/I516376/events{/privacy}","received_events_url":"https://github.wdf.sap.corp/api/v3/users/I516376/received_events","type":"User","site_admin":false},"html_url":"https://github.wdf.sap.corp/I516376/test-pr","description":null,"fork":false,"url":"https://github.wdf.sap.corp/api/v3/repos/I516376/test-pr","forks_url":"https://github.wdf.sap.corp/api/v3/repos/I516376/test-pr/forks","keys_url":"https://github.wdf.sap.corp/api/v3/repos/I516376/test-pr/keys{/key_id}","collaborators_url":"https://github.wdf.sap.corp/api/v3/repos/I516376/test-pr/collaborators{/collaborator}","teams_url":"https://github.wdf.sap.corp/api/v3/repos/I516376/test-pr/teams","hooks_url":"https://github.wdf.sap.corp/api/v3/repos/I516376/test-pr/hooks","issue_events_url":"https://github.wdf.sap.corp/api/v3/repos/I516376/test-pr/issues/events{/number}","events_url":"https://github.wdf.sap.corp/api/v3/repos/I516376/test-pr/events","assignees_url":"https://github.wdf.sap.corp/api/v3/repos/I516376/test-pr/assignees{/user}","branches_url":"https://github.wdf.sap.corp/api/v3/repos/I516376/test-pr/branches{/branch}","tags_url":"https://github.wdf.sap.corp/api/v3/repos/I516376/test-pr/tags","blobs_url":"https://github.wdf.sap.corp/api/v3/repos/I516376/test-pr/git/blobs{/sha}","git_tags_url":"https://github.wdf.sap.corp/api/v3/repos/I516376/test-pr/git/tags{/sha}","git_refs_url":"https://github.wdf.sap.corp/api/v3/repos/I516376/test-pr/git/refs{/sha}","trees_url":"https://github.wdf.sap.corp/api/v3/repos/I516376/test-pr/git/trees{/sha}","statuses_url":"https://github.wdf.sap.corp/api/v3/repos/I516376/test-pr/statuses/{sha}","languages_url":"https://github.wdf.sap.corp/api/v3/repos/I516376/test-pr/languages","stargazers_url":"https://github.wdf.sap.corp/api/v3/repos/I516376/test-pr/stargazers","contributors_url":"https://github.wdf.sap.corp/api/v3/repos/I516376/test-pr/contributors","subscribers_url":"https://github.wdf.sap.corp/api/v3/repos/I516376/test-pr/subscribers","subscription_url":"https://github.wdf.sap.corp/api/v3/repos/I516376/test-pr/subscription","commits_url":"https://github.wdf.sap.corp/api/v3/repos/I516376/test-pr/commits{/sha}","git_commits_url":"https://github.wdf.sap.corp/api/v3/repos/I516376/test-pr/git/commits{/sha}","comments_url":"https://github.wdf.sap.corp/api/v3/repos/I516376/test-pr/comments{/number}","issue_comment_url":"https://github.wdf.sap.corp/api/v3/repos/I516376/test-pr/issues/comments{/number}","contents_url":"https://github.wdf.sap.corp/api/v3/repos/I516376/test-pr/contents/{+path}","compare_url":"https://github.wdf.sap.corp/api/v3/repos/I516376/test-pr/compare/{base}...{head}","merges_url":"https://github.wdf.sap.corp/api/v3/repos/I516376/test-pr/merges","archive_url":"https://github.wdf.sap.corp/api/v3/repos/I516376/test-pr/{archive_format}{/ref}","downloads_url":"https://github.wdf.sap.corp/api/v3/repos/I516376/test-pr/downloads","issues_url":"https://github.wdf.sap.corp/api/v3/repos/I516376/test-pr/issues{/number}","pulls_url":"https://github.wdf.sap.corp/api/v3/repos/I516376/test-pr/pulls{/number}","milestones_url":"https://github.wdf.sap.corp/api/v3/repos/I516376/test-pr/milestones{/number}","notifications_url":"https://github.wdf.sap.corp/api/v3/repos/I516376/test-pr/notifications{?since,all,participating}","labels_url":"https://github.wdf.sap.corp/api/v3/repos/I516376/test-pr/labels{/name}","releases_url":"https://github.wdf.sap.corp/api/v3/repos/I516376/test-pr/releases{/id}","deployments_url":"https://github.wdf.sap.corp/api/v3/repos/I516376/test-pr/deployments","created_at":"2020-04-07T15:33:20Z","updated_at":"2020-04-07T15:36:30Z","pushed_at":"2020-04-17T10:28:34Z","git_url":"git://github.wdf.sap.corp/I516376/test-pr.git","ssh_url":"git@github.wdf.sap.corp:I516376/test-pr.git","clone_url":"https://github.wdf.sap.corp/I516376/test-pr.git","svn_url":"https://github.wdf.sap.corp/I516376/test-pr","homepage":null,"size":2,"stargazers_count":0,"watchers_count":0,"language":null,"has_issues":true,"has_projects":true,"has_downloads":true,"has_wiki":true,"has_pages":false,"forks_count":0,"mirror_url":null,"archived":false,"disabled":false,"open_issues_count":1,"license":null,"forks":0,"open_issues":1,"watchers":0,"default_branch":"master"},"enterprise":{"id":1,"slug":"sap-se","name":"SAP SE","node_id":"MDEwOkVudGVycHJpc2Ux","avatar_url":"https://github.wdf.sap.corp/avatars/b/1?","description":null,"website_url":null,"html_url":"https://github.wdf.sap.corp/enterprises/sap-se","created_at":"2019-03-16T05:31:15Z","updated_at":"2019-03-16T05:31:15Z"},"sender":{"login":"I516376","id":53960,"node_id":"MDQ6VXNlcjUzOTYw","avatar_url":"https://github.wdf.sap.corp/avatars/u/53960?","gravatar_id":"","url":"https://github.wdf.sap.corp/api/v3/users/I516376","html_url":"https://github.wdf.sap.corp/I516376","followers_url":"https://github.wdf.sap.corp/api/v3/users/I516376/followers","following_url":"https://github.wdf.sap.corp/api/v3/users/I516376/following{/other_user}","gists_url":"https://github.wdf.sap.corp/api/v3/users/I516376/gists{/gist_id}","starred_url":"https://github.wdf.sap.corp/api/v3/users/I516376/starred{/owner}{/repo}","subscriptions_url":"https://github.wdf.sap.corp/api/v3/users/I516376/subscriptions","organizations_url":"https://github.wdf.sap.corp/api/v3/users/I516376/orgs","repos_url":"https://github.wdf.sap.corp/api/v3/users/I516376/repos","events_url":"https://github.wdf.sap.corp/api/v3/users/I516376/events{/privacy}","received_events_url":"https://github.wdf.sap.corp/api/v3/users/I516376/received_events","type":"User","site_admin":false}}